{
  "version": 1,
  "updatedAt": "2026-05-31T08:00:00Z",
  "polls": [
    {
      "id": "p_2026-05-31",
      "question": {
        "hi": "क्या योगी सरकार का नया फैसला सही है?",
        "en": "Is Yogi government's new decision right?"
      },
      "options": [
        {"id": "yes", "label": {"hi": "हाँ", "en": "Yes"}, "votes": 0},
        {"id": "no", "label": {"hi": "नहीं", "en": "No"}, "votes": 0},
        {"id": "neutral", "label": {"hi": "पता नहीं", "en": "Don't know"}, "votes": 0}
      ],
      "closesAt": "2026-06-01T23:59:59Z"
    }
  ]
}
